iphttpd_apps/__init__.py
iphttpd_apps/helloworld.py
iptt/__init__.py
iptt/cli.py
iptt/entrypoints.py
iptt/iphttp/__init__.py
iptt/iphttp/client.py
iptt/iphttp/interface.py
iptt/iphttp/request.py
iptt/iphttp/server.py
iptt-1.0.5.dist-info/METADATA
iptt-1.0.5.dist-info/WHEEL
iptt-1.0.5.dist-info/entry_points.txt
iptt-1.0.5.dist-info/top_level.txt
iptt-1.0.5.dist-info/RECORD
